Lab07/SignExtender.v
module SignExtender(BusImm, Inst26, Ctrl);
	output reg [63:0] BusImm;
	input [25:0] Inst26; 
	input [1:0] Ctrl; 

	reg extBit; 
//	assign extBit = (Ctrl ? 1'b0 : Inst26[25]); 
//	assign BusImm = {{26{extBit}}, Inst26}; 
always@(*)
	begin
	if (Ctrl == 2'b00) //I type
		begin
			extBit = Inst26[21];
			BusImm = {{52{extBit}}, Inst26[21:10]};
		end
	else if (Ctrl == 2'b01) //D type
		begin
			extBit = Inst26[20];
			BusImm = {{55{extBit}}, Inst26[20:12]};	
		end
	else if (Ctrl == 2'b10) //B
		begin
			extBit = Inst26[25];
			BusImm = {{38{extBit}}, Inst26};
		end
	else if (Ctrl == 2'b11) //CBZ
		begin
			extBit = Inst26[23];
			BusImm = {{45{extBit}}, Inst26[23:5]};
		end
//	else 
	end
endmodule

Lab07/SignExtenderTest.v
`define STRLEN 15
module SignExtenderTest;

	initial
		begin
			$dumpfile("SignExtenderTest.vcd");
			$dumpvars(0,SignExtenderTest);
		end
	task passTest;
		input [63:0] actualOut, expectedOut;
		input [`STRLEN*8:0] testType;
		inout [7:0] passed;
	
		if(actualOut == expectedOut) begin $display ("%s passed", testType); passed = passed + 1; end
		else $display ("%s failed: %d should be %d", testType, actualOut, expectedOut);
	endtask
	
	task allPassed;
		input [7:0] passed;
		input [7:0] numTests;
		
		if(passed == numTests) $display ("All tests passed");
		else $display("Some tests failed");
	endtask
	
	// Inputs
	 	reg [1:0] Ctrl;
	 		reg [25:0] Inst26 ;
		reg [7:0] passed;
//	reg [63:0] b;

 	// Outputs
	 				wire [63:0] BusImm;
 					// Instantiate the Unit Under Test (UUT)
	 						SignExtender uut (
	 								.Ctrl(Ctrl), 
	 								.Inst26(Inst26),
									.BusImm(BusImm)
	 											);
				initial begin
	 	// Initialize
	 	//inputs
	 	Ctrl = 0;
		Inst26 = 0;
		passed = 0;
		//reg [63:0] b;
//		b = {{38{Inst26[25]}} + Inst26};
	
		#90; {Inst26, Ctrl} = {26'b11, 2'b10}; #10; passTest(BusImm, 63'b11, "b type input", passed);  //b
 		#90; Ctrl = 2'b00; #10; passTest(BusImm, {52{Inst26[21]}} + Inst26[21:10], "i type input", passed);  //i type
		#90; Ctrl = 2'b01; #10; passTest(BusImm, {55{Inst26[20]}} + Inst26[20:12], "d type input", passed);  //d type
		#90; Ctrl = 2'b11; #10; passTest(BusImm, {45{Inst26[23]}} + Inst26[23:5], "cbz type input", passed);  //cbz

		end
endmodule

Lab07/SignExtenderTest.vcd
$date
	Mon Apr  3 16:34:04 2023
$end
$version
	Icarus Verilog
$end
$timescale
	1s
$end
$scope module SignExtenderTest $end
$var wire 64 ! BusImm [63:0] $end
$var reg 2 " Ctrl [1:0] $end
$var reg 26 # Inst26 [25:0] $end
$var reg 8 $ passed [7:0] $end
$scope module uut $end
$var wire 2 % Ctrl [1:0] $end
$var wire 26 & Inst26 [25:0] $end
$var reg 64 ' BusImm [63:0] $end
$var reg 1 ( extBit $end
$upscope $end
$scope task allPassed $end
$var reg 8 ) numTests [7:0] $end
$var reg 8 * passed [7:0] $end
$upscope $end
$scope task passTest $end
$var reg 64 + actualOut [63:0] $end
$var reg 64 , expectedOut [63:0] $end
$var reg 8 - passed [7:0] $end
$var reg 121 . testType [120:0] $end
$upscope $end
$upscope $end
$enddefinitions $end
#0
$dumpvars
bx .
bx -
bx ,
bx +
bx *
bx )
0(
b0 '
b0 &
b0 %
b0 $
b0 #
b0 "
b0 !
$end
#90
b11 !
b11 '
b11 #
b11 &
b10 "
b10 %
#100
b1 $
b1 -
b11000100010000001110100011110010111000001100101001000000110100101101110011100000111010101110100 .
b11 ,
b11 +
#190
b0 !
b0 '
b0 "
b0 %
#200
b10 $
b10 -
b11010010010000001110100011110010111000001100101001000000110100101101110011100000111010101110100 .
b0 ,
b0 +
#290
b1 "
b1 %
#300
b11 $
b11 -
b11001000010000001110100011110010111000001100101001000000110100101101110011100000111010101110100 .
#390
b11 "
b11 %
#400
b100 $
b100 -
b110001101100010011110100010000001110100011110010111000001100101001000000110100101101110011100000111010101110100 .
